{
	"we_cooperate_with_2": "We cooperate with:",
	"we_cooperate_with_3": "This is a text",
	"we_cooperate_with_4": "This is also a text",
	"we_cooperate_with": "We cooperate with:",
	"navigate": "Navigate",
	"social": "Social",
	"facebook": "Facebook",
	"twitter": "Twitter",
	"instagram": "Instagram",
	"facebook_url":"https://www.facebook.com/",
	"twitter_url":"https://twitter.com/",
	"instagram_url":"https://www.instagram.com/",
	"contact": "Contact",
	"korv_is_owned_by":"Korv is run and owned by Webbhälsa AB (556967-0820).",
	"how_it_works": "How it works",
}
